{
    "status": {
        "ENABLE": "True"
    },
    "alarm": {
        "minmax_alarm": {
            "coolant temperature in": {
                "name": "coolant_in_temp",
                "max": 25,
                "min": 5,
                "status": 0,
                "time": 0,
                "text": "alarm: coolant temperature input out of range"
            },
            "coolant temperature out": {
                "name": "coolant_out_temp",
                "max": 35,
                "min": 10,
                "status": 3,
                "time": [
                    2025,
                    4,
                    29,
                    17,
                    0,
                    2
                ],
                "text": "alarm: coolant temperature output out of range"
            },
            "oil temperature": {
                "name": "oil_temp",
                "max": 45,
                "min": 10,
                "status": 3,
                "time": [
                    2025,
                    4,
                    29,
                    17,
                    5,
                    1
                ],
                "text": "alarm: oil temperature out of range"
            },
            "time update": {
                "name": "time",
                "max": 420,
                "min": -420,
                "status": 0,
                "time": 0,
                "text": "alarm: log file is not updating"
            }
        },
        "status_alarm": {
            "warning state": {
                "name": "warning_state",
                "status": 0,
                "time": 0,
                "text": "cryomech compressor in a warning state"
            },
            "alarm state": {
                "name": "alarm_state",
                "status": 0,
                "time": 0,
                "text": "cryomech compressor in alarm state"
            }
        }
    }
}